gstreamer_plugins_frei0r-1.27.90.data/purelib/gstreamer_plugins_frei0r/__init__.py
gstreamer_plugins_frei0r-1.27.90.data/purelib/gstreamer_plugins_frei0r/lib/frei0r-1/3dflippo.dll
gstreamer_plugins_frei0r-1.27.90.data/purelib/gstreamer_plugins_frei0r/lib/frei0r-1/B.dll
gstreamer_plugins_frei0r-1.27.90.data/purelib/gstreamer_plugins_frei0r/lib/frei0r-1/G.dll
gstreamer_plugins_frei0r-1.27.90.data/purelib/gstreamer_plugins_frei0r/lib/frei0r-1/IIRblur.dll
gstreamer_plugins_frei0r-1.27.90.data/purelib/gstreamer_plugins_frei0r/lib/frei0r-1/R.dll
gstreamer_plugins_frei0r-1.27.90.data/purelib/gstreamer_plugins_frei0r/lib/frei0r-1/RGB.dll
gstreamer_plugins_frei0r-1.27.90.data/purelib/gstreamer_plugins_frei0r/lib/frei0r-1/addition.dll
gstreamer_plugins_frei0r-1.27.90.data/purelib/gstreamer_plugins_frei0r/lib/frei0r-1/addition_alpha.dll
gstreamer_plugins_frei0r-1.27.90.data/purelib/gstreamer_plugins_frei0r/lib/frei0r-1/aech0r.dll
gstreamer_plugins_frei0r-1.27.90.data/purelib/gstreamer_plugins_frei0r/lib/frei0r-1/alpha0ps_alpha0ps.dll
gstreamer_plugins_frei0r-1.27.90.data/purelib/gstreamer_plugins_frei0r/lib/frei0r-1/alpha0ps_alphagrad.dll
gstreamer_plugins_frei0r-1.27.90.data/purelib/gstreamer_plugins_frei0r/lib/frei0r-1/alpha0ps_alphaspot.dll
gstreamer_plugins_frei0r-1.27.90.data/purelib/gstreamer_plugins_frei0r/lib/frei0r-1/alphaatop.dll
gstreamer_plugins_frei0r-1.27.90.data/purelib/gstreamer_plugins_frei0r/lib/frei0r-1/alphain.dll
gstreamer_plugins_frei0r-1.27.90.data/purelib/gstreamer_plugins_frei0r/lib/frei0r-1/alphainjection.dll
gstreamer_plugins_frei0r-1.27.90.data/purelib/gstreamer_plugins_frei0r/lib/frei0r-1/alphaout.dll
gstreamer_plugins_frei0r-1.27.90.data/purelib/gstreamer_plugins_frei0r/lib/frei0r-1/alphaover.dll
gstreamer_plugins_frei0r-1.27.90.data/purelib/gstreamer_plugins_frei0r/lib/frei0r-1/alphaxor.dll
gstreamer_plugins_frei0r-1.27.90.data/purelib/gstreamer_plugins_frei0r/lib/frei0r-1/balanc0r.dll
gstreamer_plugins_frei0r-1.27.90.dist-info/METADATA
gstreamer_plugins_frei0r-1.27.90.dist-info/WHEEL
gstreamer_plugins_frei0r-1.27.90.dist-info/top_level.txt
gstreamer_plugins_frei0r-1.27.90.dist-info/RECORD
